poetry_source_env_zp/__init__.py
poetry_source_env_zp/plugin.py
poetry_source_env_zp-2.0.8.dist-info/LICENSE.md
poetry_source_env_zp-2.0.8.dist-info/METADATA
poetry_source_env_zp-2.0.8.dist-info/WHEEL
poetry_source_env_zp-2.0.8.dist-info/entry_points.txt
poetry_source_env_zp-2.0.8.dist-info/RECORD
