Metadata-Version: 2.3
Name: poetry-source-env-zp
Version: 2.0.8
Summary: Load Poetry package sources from environment variables with pydantic > 2
License: MIT
Author: celsius narhwal
Author-email: hello@celsiusnarhwal.dev
Requires-Python: >=3.8,<4.0
Classifier: License :: OSI Approved :: MIT License
Classifier: Programming Language :: Python :: 3
Classifier: Programming Language :: Python :: 3.8
Classifier: Programming Language :: Python :: 3.9
Classifier: Programming Language :: Python :: 3.10
Classifier: Programming Language :: Python :: 3.11
Classifier: Programming Language :: Python :: 3.12
Classifier: Programming Language :: Python :: 3.13
Requires-Dist: dict-deep (>=4.1.2,<5.0.0)
Requires-Dist: poetry (>=1.5.0)
Requires-Dist: pydantic (>=2.0.0,<3.0.0)
Requires-Dist: pydantic-settings (>=2.6.1,<3.0.0)
Project-URL: Homepage, https://github.com/celsiusnarhwal/poetry-source-env
Project-URL: Repository, https://github.com/celsiusnarhwal/poetry-source-env
